Antiland/__init__.py
Antiland/account.py
Antiland/bot.py
Antiland/dialogue.py
Antiland/message.py
Antiland/message_updater.py
Antiland/user.py
Antiland/ext/__init__.py
Antiland/ext/commands/__init__.py
Antiland/ext/commands/bot.py
antiland-0.99.2.dist-info/METADATA
antiland-0.99.2.dist-info/WHEEL
antiland-0.99.2.dist-info/licenses/LICENSE
antiland-0.99.2.dist-info/RECORD
